MANIFEST.in
README.md
setup.py
libappadapter/__init__.py
libappadapter/exceptions.py
libappadapter/helpers.py
libappadapter/settings.py
libappadapter.egg-info/PKG-INFO
libappadapter.egg-info/SOURCES.txt
libappadapter.egg-info/dependency_links.txt
libappadapter.egg-info/requires.txt
libappadapter.egg-info/top_level.txt
libappadapter/application/__init__.py
libappadapter/application/app_config.py
libappadapter/application/application.py
libappadapter/application/kinds.py
libappadapter/k8s/__init__.py
libappadapter/k8s/configuration.py
libappadapter/k8s/model.py
libappadapter/k8s/operator.py
libappadapter/k8s/status.py
libappadapter/k8s/utils.py
libappadapter/namespace/__init__.py
libappadapter/namespace/namespace.py
libappadapter/quota/__init__.py
libappadapter/relations/__init__.py
libappadapter/relations/application.py
libappadapter/relations/node.py
libappadapter/relations/relations.py
libappadapter/relations/tree.py
libappadapter/templates/README.md
libappadapter/templates/init_instance_adv_configs.py
libappadapter/templates/run_test.sh
libappadapter/templates/applib/app.libsonnet
libappadapter/templates/applib/kube.libsonnet
libappadapter/templates/applib/utils.libsonnet
libappadapter/templates/applib/test/run_test.sh
libappadapter/templates/applib/test/test_app.jsonnet
libappadapter/templates/applib/test/test_app_shlex.jsonnet
libappadapter/templates/applib/test/test_utils.jsonnet
libappadapter/templates/applications/DISCOVER/1.0/dependency.jsonnet
libappadapter/templates/applications/DISCOVER/1.0/resource.jsonnet
libappadapter/templates/applications/DISCOVER/1.0/test-files/config1_dependency.jsonnet
libappadapter/templates/applications/DISCOVER/1.0/test-files/config1_dependency.jsonnet.golden
libappadapter/templates/applications/DISCOVER/1.0/test-files/config_dependency.jsonnet
libappadapter/templates/applications/DISCOVER/1.0/test-files/config_dependency.jsonnet.golden
libappadapter/templates/applications/DISCOVER/5.0/dependency.jsonnet
libappadapter/templates/applications/DISCOVER/5.0/resource.jsonnet
libappadapter/templates/applications/DISCOVER/5.0/test-files/config_dependency.jsonnet
