Metadata-Version: 1.0
Name: libappadapter
Version: 0.2.7
Summary: An abstraction of applications converted from python APi to kubernetes templates
Home-page: http://172.16.1.41:10080/TDC/libappadapter.git
Author: Transwarp
Author-email: UNKNOWN
License: Transwarp Copyright
Platform: UNKNOWN
